contextual_conv/__init__.py
contextual_conv/contextual_conv.py
contextual_conv-0.6.4.dist-info/licenses/LICENSE
contextual_conv-0.6.4.dist-info/METADATA
contextual_conv-0.6.4.dist-info/WHEEL
contextual_conv-0.6.4.dist-info/top_level.txt
contextual_conv-0.6.4.dist-info/RECORD
