Metadata-Version: 2.4
Name: contextual-conv
Version: 0.6.4
Summary: PyTorch convolutional layers with global context conditioning
Author-email: Mehdi Abbassi <mehdi.n.abbassi@gmail.com>
License: GPL-3.0-only
Project-URL: Homepage, https://github.com/abbassix/ContextualConv
Requires-Python: >=3.7
License-File: LICENSE
Provides-Extra: dev
Requires-Dist: pytest; extra == "dev"
Requires-Dist: torch; extra == "dev"
Requires-Dist: numpy; extra == "dev"
Dynamic: license-file
